mcp_client/__init__.py
mcp_client/base_client.py
mcp_client/manager.py
mcp_client/clients/__init__.py
mcp_client/clients/chatgpt_client.py
mcp_client/clients/custom_llm_client.py
mcp_client/clients/gemini_client.py
mcp_client/clients/perplexity_client.py
mcp_client/clients/utils.py
mcp_llm_client_proxy-0.3.0.dist-info/licenses/LICENSE
mcp_llm_client_proxy-0.3.0.dist-info/METADATA
mcp_llm_client_proxy-0.3.0.dist-info/WHEEL
mcp_llm_client_proxy-0.3.0.dist-info/top_level.txt
mcp_llm_client_proxy-0.3.0.dist-info/RECORD
