Metadata-Version: 2.4
Name: mcp-llm-client-proxy
Version: 0.3.0
Summary: A Multi-Client Proxy (MCP) for various LLMs with failover and flexible response formats.
Home-page: https://github.com/PrashantHalaki/mcp_llm_client
Author: Prashant Halaki
Author-email: prashanthalaki143@gmail.com
Project-URL: Bug Tracker, https://github.com/PrashantHalaki/mcp_llm_client/issues
Classifier: Programming Language :: Python :: 3
Classifier: License :: OSI Approved :: MIT License
Classifier: Operating System :: OS Independent
Classifier: Intended Audience :: Developers
Classifier: Topic :: Software Development :: Libraries :: Python Modules
Classifier: Topic :: Scientific/Engineering :: Artificial Intelligence
Requires-Python: >=3.8
License-File: LICENSE
Requires-Dist: google-generativeai>=0.8.5
Requires-Dist: openai>=1.99.1
Requires-Dist: requests>=2.32.4
Dynamic: author
Dynamic: author-email
Dynamic: classifier
Dynamic: description
Dynamic: description-content-type
Dynamic: home-page
Dynamic: license-file
Dynamic: project-url
Dynamic: requires-dist
Dynamic: requires-python
Dynamic: summary
